sequentialLogic/ringCounter/ringCounter.v
module ringCounter_4_bit (clk, ORI, out);
input clk;
input ORI;
output reg [3:0] out;
reg [3:0] D;

always @(negedge clk or ORI) begin
    if (ORI == 1'b0)
    begin 
        out[0] <= 1'b1;
        D[1] <= 1'b1;
        out[3:1] <= 3'b000;
        D[2] <= 1'b0;
        D[3] <= 1'b0;
        D[0] <= 1'b0;
    end

    else
    begin
        if (clk == 1'b0) //falling edge
        begin
            out[3:0] = D[3:0]; //blocking for updating
            
            D[3:1] <= out[2:0];
            D[0] <= out[3];
        end
    end
end
endmodule

sequentialLogic/ringCounter/ringCounter_tb.v
`timescale 1ns/1ns
`include "ringCounter.v"

module ringCounter_tb;
reg clk=0, ORI;
wire [3:0] out;

ringCounter_4_bit uut(clk, ORI, out);

always begin
    clk = ~clk;
    #10;
end

initial begin
    $dumpfile("ringCounter.vcd");
    $dumpvars(0, ringCounter_tb);
    ORI = 1'b0; #5;
    ORI = 1'b1; #150;
    $display("ring counter test done");
    $finish;
end

endmodule

sequentialLogic/ringCounter/ringCounter.vcd
$date
	Thu Dec 29 21:50:22 2022
$end
$version
	Icarus Verilog
$end
$timescale
	1ns
$end
$scope module ringCounter_tb $end
$var wire 4 ! out [3:0] $end
$var reg 1 " ORI $end
$var reg 1 # clk $end
$scope module uut $end
$var wire 1 " ORI $end
$var wire 1 # clk $end
$var reg 4 $ D [3:0] $end
$var reg 4 % out [3:0] $end
$upscope $end
$upscope $end
$enddefinitions $end
#0
$dumpvars
b1 %
b10 $
1#
0"
b1 !
$end
#5
1"
#10
b100 $
b10 !
b10 %
0#
#20
1#
#30
b1000 $
b100 !
b100 %
0#
#40
1#
#50
b1 $
b1000 !
b1000 %
0#
#60
1#
#70
b10 $
b1 !
b1 %
0#
#80
1#
#90
b100 $
b10 !
b10 %
0#
#100
1#
#110
b1000 $
b100 !
b100 %
0#
#120
1#
#130
b1 $
b1000 !
b1000 %
0#
#140
1#
#150
b10 $
b1 !
b1 %
0#
